{
  "users": [
    {
      "id": 0,
      "fullName": "----------"
    },
    {
      "id": 1,
      "fullName": "Jorg Hesser"
    },
    {
      "id": 2,
      "fullName": "Greg VonRehder"
    },
    {
      "id": 3,
      "fullName": "David Holt"
    },
    {
      "id": 4,
      "fullName": "Ayumu Tokiwa"
    },
    {
      "id": 5,
      "fullName": "Jeremy Lo"
    },
    {
      "id": 6,
      "fullName": "Ryan Roth"
    },
    {
      "id": 7,
      "fullName": "Jamie Pedersen"
    },
    {
      "id": 8,
      "fullName": "Aaron Fernando"
    }
  ],
  "projects": [
    {
      "id": 2,
      "name": "SDL4k & SDL8k",
      "supplier": "Biologic",
      "manager": "Greg VonRehder",
      "date": "2017-05-24",
      "status": "2",
      "generalNotes": "",
      "folder": "",
      "estimatedDate": "",
      "p_requestFromSupplier01a": true,
      "p_requestFromSupplier01b": true,
      "p_requestFromSupplier01c": true,
      "p_requestFromSupplier01_notes": "5/24/17: Returned 3k sample",
      "p_requestFromSupplier03a": true,
      "p_requestFromSupplier03b": true,
      "p_requestFromSupplier03_notes": "6/26/17: Jorg requested the 4k 1000-25 for high voltage testing and 600-150 for parallel testing\n5/24/17: Received 8k-600-300 FA",
      "p_requestFromSupplier04a": true,
      "p_requestFromSupplier04b": true,
      "p_requestFromSupplier04c": true,
      "p_requestFromSupplier05a": true,
      "p_requestFromSupplier05b": true,
      "p_requestFromSupplier05c": true,
      "p_requestFromSupplier06a": true,
      "p_requestFromSupplier06b": true,
      "p_requestFromSupplier06c": true,
      "p_requestFromSupplier07a": true,
      "p_requestFromSupplier07b": true,
      "p_requestFromSupplier07c": true,
      "p_requestFromSupplier08a": true,
      "p_requestFromSupplier08b": true,
      "p_requestFromSupplier08c": true,
      "p_provideToSupplier01a": true,
      "p_provideToSupplier01b": true,
      "p_provideToSupplier02a": true,
      "p_provideToSupplier02b": true,
      "p_provideToSupplier02c": true,
      "p_provideToSupplier03a": true,
      "p_provideToSupplier03b": true,
      "p_provideToSupplier05a": true,
      "p_provideToSupplier05b": true,
      "p_provideToSupplier05c": true,
      "p_provideToSupplier06a": true,
      "p_provideToSupplier06c": true,
      "p_provideToSupplier06_notes": "In Drive, needs to be changed.\n10/31/2018 Changed and submitted\n11/05/2018 DONE",
      "p_documentation01_notes": "5/24/17: Original Biologic manual was in very good condition. Fixed a minor amount of grammar. Reviewing again\n11/12/18[JP]: Waiting for specs",
      "p_tooling01a": true,
      "p_tooling02a": true,
      "p_tooling03a": true
    },
    {
      "id": 3,
      "name": "9140 Series - Project Envoy",
      "supplier": "OR-X and BK Taiwan",
      "manager": "Greg VonRehder",
      "date": "2017-06-20",
      "status": "2",
      "generalNotes": "",
      "folder": "",
      "estimatedDate": "2018",
      "p_requestFromSupplier07_notes": "8/21/17 - In progress"
    },
    {
      "id": 4,
      "name": "2680 Spectrum Analyzers",
      "manager": "David Holt",
      "date": "2017-05-25",
      "status": "2",
      "generalNotes": "",
      "folder": "",
      "p_requestFromSupplier01a": true,
      "p_requestFromSupplier01b": true,
      "p_requestFromSupplier01c": true,
      "p_requestFromSupplier01_notes": "6/21 - Thang approved this month\n8/21/17 - Thang accepted sample",
      "p_requestFromSupplier03_notes": "6/21 - Evaluating sample before requesting FA",
      "p_requestFromSupplier06a": true,
      "p_requestFromSupplier06b": true,
      "p_requestFromSupplier06c": true,
      "p_requestFromSupplier06_notes": "6/21 - Siglent sent word documents",
      "p_requestFromSupplier07c": true,
      "p_requestFromSupplier08_notes": "12/18/17 Siglent promised to send to Sean",
      "p_requestFromSupplier11_notes": "12/18/17 Ayumu to request",
      "p_provideToSupplier02_notes": "12/18/17 Sent the first IOR",
      "p_provideToSupplier03_notes": "12/18/17 Easy Spectrum software is not branded.",
      "p_provideToSupplier05c": true,
      "p_provideToSupplier05_notes": "12/18/17 Overlay sent"
    },
    {
      "id": 5,
      "name": "FRA8000",
      "manager": "David Holt",
      "date": "2017-10-09",
      "status": "2",
      "generalNotes": "",
      "folder": "",
      "p_requestFromSupplier01a": true,
      "p_requestFromSupplier01b": true,
      "p_requestFromSupplier01c": true
    },
    {
      "name": "8500B",
      "manager": "Greg VonRehder",
      "supplier": "Itech",
      "date": "2018-05-09",
      "status": "2",
      "id": 6,
      "generalNotes": "M:/Product Development/Itech/8500B",
      "folder": "",
      "p_requestFromSupplier01a": true,
      "p_requestFromSupplier01b": true,
      "p_requestFromSupplier01c": true,
      "p_requestFromSupplier02_link": "M:\\Databases\\Documents\\NwPrdEval\\ITECH 8512A ",
      "p_requestFromSupplier03a": true,
      "p_requestFromSupplier04a": true,
      "p_requestFromSupplier04b": true,
      "p_requestFromSupplier04c": true,
      "p_requestFromSupplier05a": true,
      "p_requestFromSupplier05b": true,
      "p_requestFromSupplier05c": true,
      "p_requestFromSupplier06a": true,
      "p_requestFromSupplier06b": true,
      "p_requestFromSupplier06c": true,
      "p_requestFromSupplier07a": true,
      "p_requestFromSupplier07b": false,
      "p_requestFromSupplier07c": true,
      "p_requestFromSupplier08a": false,
      "p_requestFromSupplier08b": false,
      "p_requestFromSupplier08c": false,
      "p_requestFromSupplier09c": true,
      "p_provideToSupplier01a": true,
      "p_provideToSupplier01b": true,
      "p_provideToSupplier02a": true,
      "p_provideToSupplier02b": true,
      "p_provideToSupplier02c": true,
      "p_provideToSupplier03a": true,
      "p_provideToSupplier03b": true,
      "p_provideToSupplier05a": true,
      "p_provideToSupplier05b": true,
      "p_provideToSupplier05c": true,
      "p_provideToSupplier06a": true,
      "p_provideToSupplier06c": true,
      "p_provideToSupplier06_notes": "9/10/18 -  Use the same artwork as the 8600, different label.",
      "p_provideToSupplier07b": true,
      "p_provideToSupplier08b": true
    },
    {
      "name": "9160",
      "manager": "Group",
      "date": "2018-02-05",
      "status": "2",
      "id": 7,
      "generalNotes": "",
      "folder": ""
    },
    {
      "id": 8,
      "name": "1696B - Mason Update",
      "manager": "Group",
      "date": "2018-02-05",
      "status": "2",
      "generalNotes": "",
      "folder": ""
    },
    {
      "id": 9,
      "name": "1785C - Mason Update",
      "manager": "Group",
      "date": "2018-02-05",
      "status": "2",
      "generalNotes": "",
      "folder": ""
    },
    {
      "id": 10,
      "name": "MPS - ORX",
      "manager": "Group",
      "date": "2018-02-05",
      "status": "2",
      "generalNotes": "",
      "folder": ""
    },
    {
      "id": 11,
      "name": "XLNB",
      "manager": "Group",
      "date": "2018-02-05",
      "status": "2",
      "generalNotes": "",
      "folder": ""
    },
    {
      "id": 12,
      "name": "PVSMR",
      "manager": "Group",
      "date": "2018-02-05",
      "status": "2",
      "generalNotes": "",
      "folder": ""
    },
    {
      "id": 13,
      "name": "3600 Series Hipot",
      "supplier": "Biologic",
      "manager": "Greg VonRehder",
      "date": "2018-05-22",
      "status": "2",
      "generalNotes": "",
      "folder": "",
      "estimatedDate": "2018-09-01"
    },
    {
      "id": 14,
      "name": "BA8100",
      "manager": "David Holt",
      "date": "2018-06-04",
      "status": "2",
      "generalNotes": "",
      "folder": ""
    },
    {
      "name": "Test Project",
      "supplier": "BK",
      "manager": "Greg VonRehder",
      "date": "2018-10-16",
      "estimatedDate": "2018-10-31",
      "generalNotes": "I want donuts.",
      "id": 15,
      "p_requestFromSupplier01a": false,
      "p_requestFromSupplier01b": true,
      "p_requestFromSupplier01c": true,
      "p_requestFromSupplier01_notes": "The samples are completed.",
      "p_requestFromSupplier02_link": "M:/Common/Product Development/Some link",
      "p_requestFromSupplier03a": true,
      "p_requestFromSupplier03b": false,
      "p_requestFromSupplier03c": true,
      "p_requestFromSupplier03_notes": "Notes two",
      "p_requestFromSupplier04a": true,
      "p_requestFromSupplier04b": true,
      "p_requestFromSupplier04c": true,
      "p_requestFromSupplier04_notes": "Notes 3",
      "p_requestFromSupplier05a": true,
      "p_requestFromSupplier05b": false,
      "p_requestFromSupplier05c": false,
      "p_requestFromSupplier05_notes": "Notes 4",
      "p_requestFromSupplier06a": false,
      "p_requestFromSupplier06b": true,
      "p_requestFromSupplier06c": false,
      "p_requestFromSupplier06_notes": "Notes 5",
      "p_requestFromSupplier07a": true,
      "p_requestFromSupplier07b": false,
      "p_requestFromSupplier07c": true,
      "p_requestFromSupplier07_notes": "Notes 6",
      "p_requestFromSupplier08a": true,
      "p_requestFromSupplier08b": true,
      "p_requestFromSupplier08c": true,
      "p_requestFromSupplier08_notes": "Notes 7",
      "p_requestFromSupplier09a": true,
      "p_requestFromSupplier09b": true,
      "p_requestFromSupplier09c": false,
      "p_requestFromSupplier09_notes": "Notes 8",
      "p_requestFromSupplier10a": false,
      "p_requestFromSupplier10b": true,
      "p_requestFromSupplier10c": true,
      "p_requestFromSupplier10_notes": "Notes 9",
      "p_requestFromSupplier11a": true,
      "p_requestFromSupplier11b": true,
      "p_requestFromSupplier11c": false,
      "p_requestFromSupplier11_notes": "Notes 10",
      "p_provideToSupplier01a": false,
      "p_provideToSupplier01b": true,
      "p_provideToSupplier01_notes": "This is the provide notes.",
      "p_provideToSupplier02a": false,
      "p_provideToSupplier02b": true,
      "p_provideToSupplier02c": false,
      "p_provideToSupplier02_notes": "This is notes row 2.",
      "p_provideToSupplier03a": true,
      "p_provideToSupplier03b": false,
      "p_provideToSupplier03_notes": "This is notes row 3.",
      "p_provideToSupplier04a": true,
      "p_provideToSupplier04b": true,
      "p_provideToSupplier04_notes": "This is notes row 4.",
      "p_provideToSupplier05a": false,
      "p_provideToSupplier05b": true,
      "p_provideToSupplier05c": false,
      "p_provideToSupplier05_notes": "This is row 5.",
      "p_provideToSupplier06a": false,
      "p_provideToSupplier06b": true,
      "p_provideToSupplier06c": true,
      "p_provideToSupplier06_notes": "This is row 6.",
      "p_provideToSupplier07a": true,
      "p_provideToSupplier07b": true,
      "p_provideToSupplier07_notes": "Notes 3",
      "p_provideToSupplier08a": false,
      "p_provideToSupplier08b": true,
      "p_provideToSupplier08_notes": "Notes 4",
      "p_documentation01a": true,
      "p_documentation01b": false,
      "p_documentation01c": false,
      "p_documentation01d": true,
      "p_documentation01e": true,
      "p_documentation01f": false,
      "p_documentation01g": true,
      "p_documentation01h": false,
      "p_documentation01i": false,
      "p_documentation01_link": "File URL 1",
      "p_documentation01_notes": "Notes 1",
      "p_documentation02a": true,
      "p_documentation02b": false,
      "p_documentation02c": false,
      "p_documentation02d": false,
      "p_documentation02e": true,
      "p_documentation02f": false,
      "p_documentation02g": false,
      "p_documentation02h": true,
      "p_documentation02i": true,
      "p_documentation02_link": "File URL 2",
      "p_documentation02_notes": "Notes 2",
      "p_tooling01a": false,
      "p_tooling01_review": "Greg",
      "p_tooling01b": true,
      "p_tooling02a": true,
      "p_tooling02_review": "Dave",
      "p_tooling03a": false,
      "p_tooling03_review": "Ryan",
      "p_tooling03b": true,
      "p_tooling04_link": "M:/Some Folder Link/Folder here",
      "p_tooling05a": true,
      "p_tooling05_review": "Ahmad",
      "p_tooling06_notes": "These are some notes here.",
      "p_pricing01a": true,
      "p_pricing01_review": "Reviewer A",
      "p_pricing01_link": "Files URL here",
      "p_pricing01_notes": "Notes here",
      "p_pricing02a": false,
      "p_pricing02_review": "Reviewer B",
      "p_pricing03a": false,
      "p_promotion01a": true,
      "p_promotion01_review": "Reviewer A",
      "p_promotion02a": true,
      "p_promotion02b": true,
      "p_promotion03a": false,
      "p_promotion03_review": "Reviewer B",
      "p_promotion04a": true,
      "p_promotion05a": false,
      "p_promotion05_review": "Review C",
      "p_promotion05b": false,
      "p_promotion06a": false,
      "p_promotion06_review": "Review D",
      "p_promotion06b": false,
      "p_promotion07a": false,
      "p_promotion07_review": "Review F",
      "p_promotion07b": false,
      "p_promotion08_notes": "These are the section notes."
    }
  ],
  "completed": [
    {
      "id": 1,
      "name": "603B",
      "status": 1,
      "date": "2017-05-25",
      "dateCompleted": "10/17/2018"
    },
    {
      "id": 14,
      "name": "BA8100",
      "status": 1,
      "date": "2018-06-04",
      "dateCompleted": "11/19/2018"
    },
    {
      "id": 13,
      "name": "3600 Series Hipot",
      "status": 1,
      "date": "2018-05-22",
      "dateCompleted": "11/19/2018"
    },
    {
      "id": 15,
      "name": "Test Project",
      "status": 1,
      "date": "2018-10-16",
      "dateCompleted": "11/19/2018"
    },
    {
      "id": 12,
      "name": "PVSMR",
      "status": 1,
      "date": "2018-02-05",
      "dateCompleted": "11/19/2018"
    },
    {
      "id": 7,
      "name": "9160",
      "status": 1,
      "date": "2018-02-05",
      "dateCompleted": "11/19/2018"
    },
    {
      "id": 5,
      "name": "FRA8000",
      "status": 1,
      "date": "2017-10-09",
      "dateCompleted": "11/19/2018"
    },
    {
      "id": 11,
      "name": "XLNB",
      "status": 1,
      "date": "2018-02-05",
      "dateCompleted": "11/19/2018"
    }
  ],
  "pricing": [
    {
      "id": 1,
      "originID": 2,
      "bk_modelno": "SDL-600-150",
      "product_notes": "",
      "vendor": "SDL-600-150",
      "desc": "4KW 3U Programmable DC Electronic Load",
      "direct_cost": "",
      "country": 1,
      "price": "",
      "price_class": 2,
      "product_class": 4,
      "warranty": 3,
      "material": 4,
      "priority_class": "B",
      "serial_ID": 531,
      "AC_line": 1,
      "min_ord_qty": "",
      "ini_ord_qty": "",
      "arrival_date": "",
      "arrival_qty": ""
    },
    {
      "id": 2,
      "originID": 2,
      "bk_modelno": "SDL-800-75",
      "product_notes": "",
      "vendor": "SDL-800-75",
      "desc": "4KW 3U Programmable DC Electronic Load",
      "direct_cost": "",
      "country": 1,
      "price": "",
      "price_class": 2,
      "product_class": 4,
      "warranty": "",
      "material": 4,
      "priority_class": "B",
      "serial_ID": 532,
      "AC_line": 1,
      "min_ord_qty": "",
      "ini_ord_qty": "",
      "arrival_date": "",
      "arrival_qty": ""
    },
    {
      "id": 2,
      "originID": 2,
      "bk_modelno": "SDL-1000-25",
      "product_notes": "",
      "vendor": "SDL-1000-25",
      "desc": "4KW 3U Programmable DC Electronic Load",
      "direct_cost": "",
      "country": 1,
      "price": "",
      "price_class": 2,
      "product_class": 4,
      "warranty": "",
      "material": 4,
      "priority_class": "B",
      "serial_ID": 533,
      "AC_line": 1,
      "min_ord_qty": "",
      "ini_ord_qty": "",
      "arrival_date": "",
      "arrival_qty": ""
    },
    {
      "id": 2,
      "originID": 2,
      "bk_modelno": "SDL-600-300",
      "product_notes": "",
      "vendor": "SDL-600-300",
      "desc": "8kW 3U Programmable DC Electronic Load",
      "direct_cost": "",
      "country": 1,
      "price": "",
      "price_class": 2,
      "product_class": 4,
      "warranty": "",
      "material": 4,
      "priority_class": "B",
      "serial_ID": 534,
      "AC_line": 1,
      "min_ord_qty": "",
      "ini_ord_qty": "",
      "arrival_date": "",
      "arrival_qty": ""
    },
    {
      "id": 2,
      "originID": 2,
      "bk_modelno": "SDL-1000-150",
      "product_notes": "",
      "vendor": "SDL-1000-150",
      "desc": "8kW 5U Programmable DC Electronic Load",
      "direct_cost": "",
      "country": 1,
      "price": "",
      "price_class": 2,
      "product_class": 4,
      "warranty": "",
      "material": 4,
      "priority_class": "B",
      "serial_ID": 535,
      "AC_line": 1,
      "min_ord_qty": "",
      "ini_ord_qty": "",
      "arrival_date": "",
      "arrival_qty": ""
    },
    {
      "id": 2,
      "originID": 2,
      "bk_modelno": "SDL-1000-50",
      "product_notes": "",
      "vendor": "SDL-1000-50",
      "desc": "8kW 3U Programmable DC Electronic Load",
      "direct_cost": "",
      "country": 1,
      "price": "",
      "price_class": 2,
      "product_class": 4,
      "warranty": "",
      "material": 4,
      "priority_class": "B",
      "serial_ID": 536,
      "AC_line": 1,
      "min_ord_qty": "",
      "ini_ord_qty": "",
      "arrival_date": "",
      "arrival_qty": ""
    },
    {
      "id": 2,
      "originID": 4,
      "bk_modelno": "2682",
      "product_notes": "Note: Priority class should be N",
      "vendor": "SSA3021X",
      "desc": "2.1 GHz Spectrum Analyzer with Tracking Generator",
      "direct_cost": "$1,117.00",
      "country": 1,
      "price": "$2,499.00",
      "price_class": 2,
      "product_class": 21,
      "warranty": 3,
      "material": 14,
      "priority_class": "A",
      "serial_ID": "",
      "AC_line": 1,
      "min_ord_qty": "",
      "ini_ord_qty": "",
      "arrival_date": "",
      "arrival_qty": ""
    },
    {
      "id": 2,
      "originID": 4,
      "bk_modelno": "2683",
      "product_notes": "Note: Product class should be N",
      "vendor": "SSA3032X",
      "desc": "3.2 GHz Spectrum Analyzer with Tracking Generator",
      "direct_cost": "$1,817.00",
      "country": 2,
      "price": "$3,998.00",
      "price_class": 2,
      "product_class": 21,
      "warranty": 3,
      "material": 14,
      "priority_class": "A",
      "serial_ID": "",
      "AC_line": 1,
      "min_ord_qty": "",
      "ini_ord_qty": "",
      "arrival_date": "",
      "arrival_qty": ""
    },
    {
      "id": 2,
      "originID": 4,
      "bk_modelno": "EMI2680",
      "product_notes": "Note: Product class should be ACC",
      "vendor": "EMI-SSA3000X",
      "desc": "EMI Measurement activation license",
      "direct_cost": "$327.00",
      "country": 1,
      "price": "$500.00",
      "price_class": 1,
      "product_class": 1,
      "warranty": "n",
      "material": 1,
      "priority_class": "B",
      "serial_ID": "",
      "AC_line": 5,
      "min_ord_qty": "",
      "ini_ord_qty": "",
      "arrival_date": "",
      "arrival_qty": ""
    },
    {
      "id": 2,
      "originID": 4,
      "bk_modelno": "AM2680",
      "product_notes": "Note: Product class should be ACC",
      "vendor": "AMK-SSA3000X",
      "desc": "Advanced Measurement activtion license",
      "direct_cost": "$304.00",
      "country": 2,
      "price": "$400.00",
      "price_class": 1,
      "product_class": 1,
      "warranty": "n",
      "material": 1,
      "priority_class": "B",
      "serial_ID": "",
      "AC_line": 5,
      "min_ord_qty": "",
      "ini_ord_qty": "",
      "arrival_date": "",
      "arrival_qty": ""
    },
    {
      "id": 2,
      "originID": 4,
      "bk_modelno": "RFL2680",
      "product_notes": "Note: Product class should be ACC",
      "vendor": "Refl-SSA3000X",
      "desc": "Reflection Measurement Activation License",
      "direct_cost": "$101.00",
      "country": 2,
      "price": "$290.00",
      "price_class": 1,
      "product_class": 1,
      "warranty": "",
      "material": 1,
      "priority_class": "B",
      "serial_ID": "",
      "AC_line": 5,
      "min_ord_qty": "",
      "ini_ord_qty": "",
      "arrival_date": "",
      "arrival_qty": ""
    },
    {
      "id": 2,
      "originID": 4,
      "bk_modelno": "RB2680",
      "product_notes": "Note: Product class should be ACC",
      "vendor": "RB3X20",
      "desc": "Reflection Bridge",
      "direct_cost": "$235.00",
      "country": 2,
      "price": "$375.00",
      "price_class": 1,
      "product_class": 1,
      "warranty": "n",
      "material": 1,
      "priority_class": "B",
      "serial_ID": "",
      "AC_line": 5,
      "min_ord_qty": "",
      "ini_ord_qty": "",
      "arrival_date": "",
      "arrival_qty": ""
    },
    {
      "id": 2,
      "originID": 4,
      "bk_modelno": "NRF2680",
      "product_notes": "Note: Product class should be ACC",
      "vendor": "RBSSA3X20",
      "desc": "Reflection bridge hardware and license kit",
      "direct_cost": "$336.00",
      "country": 2,
      "price": "$700.00",
      "price_class": 1,
      "product_class": 1,
      "warranty": "n",
      "material": 1,
      "priority_class": "B",
      "serial_ID": "",
      "AC_line": 5,
      "min_ord_qty": "",
      "ini_ord_qty": "",
      "arrival_date": "",
      "arrival_qty": ""
    },
    {
      "id": 2,
      "originID": 4,
      "bk_modelno": "CT3331-100",
      "product_notes": "",
      "vendor": "CT3331-100",
      "desc": " 12.4GHz 50ohm 100cm RF Cable with N to N male connector",
      "direct_cost": "$112.69",
      "country": 11,
      "price": "$230.00",
      "price_class": 1,
      "product_class": 1,
      "warranty": "",
      "material": 1,
      "priority_class": "A",
      "serial_ID": "",
      "AC_line": 5,
      "min_ord_qty": 1,
      "ini_ord_qty": 5,
      "arrival_date": "",
      "arrival_qty": ""
    },
    {
      "id": 2,
      "originID": 13,
      "bk_modelno": "3602",
      "product_notes": "",
      "vendor": "TH9310",
      "desc": "Hipot Safety Tester 10mAAC",
      "direct_cost": "$476.00",
      "country": 2,
      "price": "$1,142.00",
      "price_class": 3,
      "product_class": 14,
      "warranty": 3,
      "material": 9,
      "priority_class": "A",
      "serial_ID": "",
      "AC_line": 2,
      "min_ord_qty": "",
      "ini_ord_qty": "",
      "arrival_date": "",
      "arrival_qty": ""
    },
    {
      "id": 2,
      "originID": 13,
      "bk_modelno": "3603",
      "product_notes": "",
      "vendor": "TH9320",
      "desc": "Hipot Safety Tester 20mAAC",
      "direct_cost": "$554.00",
      "country": 2,
      "price": "$1,440.00",
      "price_class": 3,
      "product_class": 14,
      "warranty": 3,
      "material": 9,
      "priority_class": "A",
      "serial_ID": "",
      "AC_line": 2,
      "min_ord_qty": "",
      "ini_ord_qty": "",
      "arrival_date": "",
      "arrival_qty": ""
    },
    {
      "id": 2,
      "originID": 13,
      "bk_modelno": "3601",
      "product_notes": "",
      "vendor": "TH9310B",
      "desc": "Hipot Safety Tester 10mAAC",
      "direct_cost": "$330.00",
      "country": 2,
      "price": "$809.00",
      "price_class": 3,
      "product_class": 14,
      "warranty": 3,
      "material": 9,
      "priority_class": "A",
      "serial_ID": "",
      "AC_line": 2,
      "min_ord_qty": "",
      "ini_ord_qty": "",
      "arrival_date": "",
      "arrival_qty": ""
    },
    {
      "id": 2,
      "originID": 13,
      "bk_modelno": "3601",
      "product_notes": "Product class and Priority class should be same as TLDK1",
      "vendor": "TH90003R/B",
      "desc": "Replacement HV test lead set for 3600 series",
      "direct_cost": "$20.00",
      "country": 2,
      "price": "$55.00",
      "price_class": 1,
      "product_class": 1,
      "warranty": "n",
      "material": 1,
      "priority_class": "A",
      "serial_ID": "",
      "AC_line": 5,
      "min_ord_qty": "",
      "ini_ord_qty": "",
      "arrival_date": "",
      "arrival_qty": ""
    },
    {
      "id": 2,
      "originID": 14,
      "bk_modelno": "BA8100",
      "product_notes": "",
      "vendor": "BA8100",
      "desc": "EIS Battery Analyzer",
      "direct_cost": "$1363.63",
      "country": 1,
      "price": "$3000.00",
      "price_class": 3,
      "product_class": 2,
      "warranty": 1,
      "material": 2,
      "priority_class": "A",
      "serial_ID": "546",
      "AC_line": 1,
      "min_ord_qty": "",
      "ini_ord_qty": "",
      "arrival_date": "",
      "arrival_qty": ""
    },
    {
      "originID": "",
      "bk_modelno": ".",
      "product_notes": ".",
      "vendor": ".",
      "desc": ".",
      "direct_cost": ".",
      "country": ".",
      "price": ".",
      "price_class": "",
      "product_class": ".",
      "warranty": ".",
      "material": ".",
      "priority_class": ".",
      "serial_ID": ".",
      "AC_line": ".",
      "min_ord_qty": "",
      "ini_ord_qty": ".",
      "arrival_date": "",
      "arrival_qty": ".",
      "id": 3
    }
  ]
}